shell_cmd/__init__.py
shell_cmd-1.0.2.dist-info/LICENSE
shell_cmd-1.0.2.dist-info/METADATA
shell_cmd-1.0.2.dist-info/WHEEL
shell_cmd-1.0.2.dist-info/top_level.txt
shell_cmd-1.0.2.dist-info/RECORD
