Metadata-Version: 2.1
Name: shell-cmd
Version: 1.0.2
Summary: Execute shell commands
Home-page: UNKNOWN
Author: Arturo Fernandez
License: UNKNOWN
Project-URL: Code, https://github.com/bsnux/shell-cmd
Platform: UNKNOWN
Classifier: Programming Language :: Python
Classifier: License :: OSI Approved :: MIT License
Classifier: Operating System :: POSIX :: Linux
Requires-Python: >=2.7
